wikilabels/__init__.py
wikilabels/wikilabels.py
wikilabels/database/__init__.py
wikilabels/database/campaigns.py
wikilabels/database/collection.py
wikilabels/database/db.py
wikilabels/database/errors.py
wikilabels/database/labels.py
wikilabels/database/schema-testdata.sql
wikilabels/database/schema.sql
wikilabels/database/tasks.py
wikilabels/database/worksets.py
wikilabels/i18n/ar.json
wikilabels/i18n/ast.json
wikilabels/i18n/ba.json
wikilabels/i18n/bn.json
wikilabels/i18n/br.json
wikilabels/i18n/ce.json
wikilabels/i18n/de.json
wikilabels/i18n/diq.json
wikilabels/i18n/en-gb.json
wikilabels/i18n/en.json
wikilabels/i18n/eo.json
wikilabels/i18n/es.json
wikilabels/i18n/fa.json
wikilabels/i18n/fi.json
wikilabels/i18n/fr.json
wikilabels/i18n/gl.json
wikilabels/i18n/he.json
wikilabels/i18n/hu-formal.json
wikilabels/i18n/hu.json
wikilabels/i18n/id.json
wikilabels/i18n/it.json
wikilabels/i18n/ja.json
wikilabels/i18n/khw.json
wikilabels/i18n/ko.json
wikilabels/i18n/ksh.json
wikilabels/i18n/lb.json
wikilabels/i18n/lt.json
wikilabels/i18n/mk.json
wikilabels/i18n/nl.json
wikilabels/i18n/no.json
wikilabels/i18n/oc.json
wikilabels/i18n/olo.json
wikilabels/i18n/pl.json
wikilabels/i18n/ps.json
wikilabels/i18n/pt-br.json
wikilabels/i18n/pt.json
wikilabels/i18n/qqq.json
wikilabels/i18n/ru.json
wikilabels/i18n/sv.json
wikilabels/i18n/tr.json
wikilabels/i18n/uk.json
wikilabels/i18n/ur.json
wikilabels/i18n/vi.json
wikilabels/i18n/zh-hans.json
wikilabels/i18n/zh-hant.json
wikilabels/util/__init__.py
wikilabels/util/tsv.py
wikilabels/util/wikimedia.py
wikilabels/utilities/__init__.py
wikilabels/utilities/dev_server.py
wikilabels/utilities/load_schema.py
wikilabels/utilities/new_campaign.py
wikilabels/utilities/remove_expired_tasks.py
wikilabels/utilities/task_inserts.py
wikilabels/wsgi/__init__.py
wikilabels/wsgi/assets.py
wikilabels/wsgi/preprocessors.py
wikilabels/wsgi/responses.py
wikilabels/wsgi/server.py
wikilabels-0.4.0.dist-info/DESCRIPTION.rst
wikilabels-0.4.0.dist-info/METADATA
wikilabels-0.4.0.dist-info/RECORD
wikilabels-0.4.0.dist-info/WHEEL
wikilabels-0.4.0.dist-info/entry_points.txt
wikilabels-0.4.0.dist-info/metadata.json
wikilabels-0.4.0.dist-info/top_level.txt
