Metadata-Version: 2.0
Name: wikilabels
Version: 0.4.0
Summary: A generalized data labeling system for use in MediaWiki wikis
Home-page: https://github.com/halfak/Wiki-Labels
Author: Aaron Halfaker
Author-email: ahalfaker@wikimedia.org
License: MIT
Platform: UNKNOWN
Classifier: Programming Language :: Python :: 3
Classifier: Development Status :: 3 - Alpha
Classifier: License :: OSI Approved :: MIT License
Classifier: Intended Audience :: Science/Research
Classifier: Intended Audience :: System Administrators
Classifier: Intended Audience :: Developers
Classifier: Operating System :: OS Independent
Classifier: Topic :: Utilities
Classifier: Topic :: Scientific/Engineering
Requires-Dist: Beaker (>=1.7.0,<1.7.999)
Requires-Dist: Flask (>=0.10.1,<0.10.999)
Requires-Dist: Flask-Assets (>=0.12,<0.999)
Requires-Dist: Flask-Cors (>=2.1.2,<2.1.999)
Requires-Dist: Flask-Jsonpify (>=1.5.0,<1.5.999)
Requires-Dist: PyExecJS (>=1.1.0,<1.1.999)
Requires-Dist: UgliPyJS (>=0.2.5,<0.2.999)
Requires-Dist: cssmin (>=0.2.0,<0.9.999)
Requires-Dist: docopt (>=0.6.2,<0.6.999)
Requires-Dist: flask-oojsui (>=0.0.2,<0.0.999)
Requires-Dist: jsmin (>=2.2.1,<2.9.999)
Requires-Dist: mediawiki-utilities (>=0.4.18,<0.4.999)
Requires-Dist: mwoauth (>=0.2.4,<0.2.999)
Requires-Dist: psycopg2 (>=2.6.1,<2.6.999)
Requires-Dist: pyOpenSSL (>=0.15.1,<0.15.999)
Requires-Dist: pylibmc (>=1.5.0,<1.5.999)
Requires-Dist: yamlconf (>=0.1.0,<0.2.999)
